nlpo3/__init__.py
nlpo3/_nlpo3_python_backend.cp314t-win_amd64.pyd
nlpo3/_nlpo3_python_backend.pyi
nlpo3/py.typed
nlpo3-1.4.0.dist-info/licenses/LICENSE
nlpo3-1.4.0.dist-info/METADATA
nlpo3-1.4.0.dist-info/WHEEL
nlpo3-1.4.0.dist-info/top_level.txt
nlpo3-1.4.0.dist-info/RECORD
