Metadata-Version: 2.4
Name: nlpo3
Version: 1.4.0
Summary: Python binding for nlpO3 Thai language processing library in Rust
Author: Thanathip Suntorntip, Arthit Suriyawongkul
Author-email: Wannaphong Phatthiyaphaibun <wannaphong@yahoo.com>
License-Expression: Apache-2.0
Project-URL: homepage, https://github.com/PyThaiNLP/nlpo3/tree/main/nlpo3-python
Project-URL: repository, https://github.com/PyThaiNLP/nlpo3/
Keywords: thai,tokenizer,tokenization,text-processing,nlp,word-segmentation,pythainlp
Classifier: Development Status :: 5 - Production/Stable
Classifier: Programming Language :: Python :: 3 :: Only
Classifier: Programming Language :: Python :: 3.9
Classifier: Programming Language :: Python :: 3.10
Classifier: Programming Language :: Python :: 3.11
Classifier: Programming Language :: Python :: 3.12
Classifier: Programming Language :: Python :: 3.13
Classifier: Programming Language :: Python :: 3.14
Classifier: Programming Language :: Python :: Implementation :: CPython
Classifier: Programming Language :: Python :: Implementation :: PyPy
Classifier: Intended Audience :: Developers
Classifier: Natural Language :: Thai
Classifier: Topic :: Text Processing :: Linguistic
Classifier: Topic :: Software Development :: Libraries :: Python Modules
Classifier: Typing :: Typed
Requires-Python: >=3.9
License-File: LICENSE
Dynamic: license-file
